salomos/__init__.py
salomos/db_manager.py
salomos/dsl_processor.py
salomos/example_function.py
salomos/example_module.py
salomos/salomos.py
salomos-0.2.2.dist-info/LICENSE
salomos-0.2.2.dist-info/METADATA
salomos-0.2.2.dist-info/WHEEL
salomos-0.2.2.dist-info/entry_points.txt
salomos-0.2.2.dist-info/top_level.txt
salomos-0.2.2.dist-info/RECORD
