Metadata-Version: 2.1
Name: salomos
Version: 0.2.2
Summary: Salomos is a Python package that provides a domain-specific language (DSL) processor for executing commands based on sentences stored in a SQLite database.
Home-page: https://python.dobyemail.com
Author: Tom Sapletta
Author-email: info@softreck.dev
Classifier: Development Status :: 3 - Alpha
Classifier: Intended Audience :: Developers
Classifier: License :: OSI Approved :: Apache Software License
Classifier: Operating System :: OS Independent
Classifier: Programming Language :: Python :: 3
Classifier: Programming Language :: Python :: 3.6
Classifier: Programming Language :: Python :: 3.7
Classifier: Programming Language :: Python :: 3.8
Classifier: Programming Language :: Python :: 3.9
License-File: LICENSE
Requires-Dist: sqlite3
